suntao_test_0/__init__.py
suntao_test_0/__version__.py
suntao_test_0/core.py
suntao_test_0-0.0.4.dist-info/DESCRIPTION.rst
suntao_test_0-0.0.4.dist-info/METADATA
suntao_test_0-0.0.4.dist-info/RECORD
suntao_test_0-0.0.4.dist-info/WHEEL
suntao_test_0-0.0.4.dist-info/metadata.json
suntao_test_0-0.0.4.dist-info/top_level.txt
