Metadata-Version: 2.0
Name: suntao-test-0
Version: 0.0.4
Summary: My short description for my project.
Home-page: https://github.com/suntao2012/***
Author: Sun Tao
Author-email: tao.a.sun@intel.com
License: MIT
Platform: UNKNOWN
Classifier: License :: OSI Approved :: MIT License
Classifier: Programming Language :: Python
Classifier: Programming Language :: Python :: 3
Classifier: Programming Language :: Python :: 3.4
Classifier: Programming Language :: Python :: Implementation :: CPython
Classifier: Programming Language :: Python :: Implementation :: PyPy
Requires-Python: >=3.4.3
Requires-Dist: pyecore
